{
  "period": {
    "start": "2025-06-26",
    "end": "2025-06-27",
    "days": 1
  },
  "data_volume": {
    "total_snapshots": 100,
    "daily_average": 100.0,
    "unique_trades": 100
  },
  "completeness": {
    "timestamp": 1.0,
    "trade_id": 1.0,
    "snapshot_type": 0.0,
    "market_snapshot": 0.0,
    "battle_navale_result": 0.0,
    "overall": 0.4
  },
  "consistency": {
    "timestamp_order": true,
    "duplicate_trades": "0",
    "invalid_values": 0
  },
  "anomalies": [
    "3 outliers d\u00e9tect\u00e9s dans slippage_ticks"
  ],
  "recommendations": [
    "Am\u00e9liorer la capture des champs obligatoires"
  ],
  "quality_score": 0.75,
  "quality_level": "ACCEPTABLE"
}